{
  "trackers": [
    {"Name": "32pages", "Abbreviation": "32P", "Type": "Comics", "Codebase": "Gazelle", "Users": "5,163", "Torrents": "45,544", "Peers": "280,094", "Ratio": "Yes", "Ratio Diff": "-", "Freeleech": "-", "Points": "Yes", "Hit & Run": "-", "Birthdate": "-", "Join": "Application, Invite, Recruitment", "Join Diff": "-", "Updated": "12-30-2019"},
    {"Name": "Aidoru!Online", "Abbreviation": "-", "Type": "Music, TV", "Codebase": "Custom", "Users": "34,071", "Torrents": "155,144", "Peers": "-", "Ratio": "Yes", "Ratio Diff": "Easy", "Freeleech": "-", "Points": "No", "Hit & Run": "-", "Birthdate": "2017", "Join": "Invite, Open", "Join Diff": "Easy", "Updated": "12-30-2019"},
    {"Name": "AlphaRatio", "Abbreviation": "AR", "Type": "General, Scene", "Codebase": "Gazelle", "Users": "17,156", "Torrents": "200,991", "Peers": "601,951", "Ratio": "Yes", "Ratio Diff": "Easy", "Freeleech": "-", "Points": "Yes", "Hit & Run": "-", "Birthdate": "2014", "Join": "Invite, Open", "Join Diff": "Easy", "Updated": "12-30-2019"},
    {"Name": "AnimeBytes", "Abbreviation": "AB", "Type": "Anime", "Codebase": "Gazelle", "Users": "16,593", "Torrents": "175,975", "Peers": "1,457,776", "Ratio": "Yes", "Ratio Diff": "Easy", "Freeleech": "-", "Points": "Yes", "Hit & Run": "-", "Birthdate": "-", "Join": "Invite, Recruitment", "Join Diff": "-", "Updated": "12-30-2019"},
    {"Name": "AnimeTorrents", "Abbreviation": "ANT", "Type": "Anime", "Codebase": "XBTIT", "Users": "27,411", "Torrents": "18,147", "Peers": "90,708", "Ratio": "Yes", "Ratio Diff": "-", "Freeleech": "-", "Points": "Yes", "Hit & Run": "-", "Birthdate": "-", "Join": "Application, Invite", "Join Diff": "-", "Updated": "12-29-2019"},
    {"Name": "Anthelion", "Abbreviation": "-", "Type": "Movie", "Codebase": "Gazelle", "Users": "1,576", "Torrents": "6,263", "Peers": "14,680", "Ratio": "Yes", "Ratio Diff": "Easy", "Freeleech": "-", "Points": "Yes", "Hit & Run": "-", "Birthdate": "-", "Join": "Invite, Recruitment", "Join Diff": "Easy", "Updated": "12-30-2019"},
    {"Name": "AsianCinema", "Abbreviation": "ACM", "Type": "Movie, TV, Music", "Codebase": "UNIT3D", "Users": "9,089", "Torrents": "5,504", "Peers": "25,063", "Ratio": "Yes", "Ratio Diff": "Easy", "Freeleech": "Yes", "Points": "Yes", "Hit & Run": "Yes", "Birthdate": "-", "Join": "Application, Invite", "Join Diff": "-", "Updated": "12-29-2019"},
    {"Name": "Audionews", "Abbreviation": "-", "Type": "Music Production", "Codebase": "-", "Users": "128,656", "Torrents": "98,150", "Peers": "-", "Ratio": "Yes", "Ratio Diff": "Hard", "Freeleech": "-", "Points": "No", "Hit & Run": "-", "Birthdate": "-", "Join": "Invite, Open", "Join Diff": "Easy", "Updated": "12-30-2019"},
    {"Name": "AvistaZ", "Abbreviation": "-", "Type": "Movie, TV, Music", "Codebase": "Custom", "Users": "141,484", "Torrents": "61,359", "Peers": "412,380", "Ratio": "Yes", "Ratio Diff": "Medium", "Freeleech": "Yes", "Points": "Yes", "Hit & Run": "Yes", "Birthdate": "-", "Join": "Application, Invite", "Join Diff": "-", "Updated": "12-30-2019"},
    {"Name": "AwesomeHD", "Abbreviation": "AHD", "Type": "Movie, TV", "Codebase": "Gazelle", "Users": "8,459", "Torrents": "50,962", "Peers": "438,081", "Ratio": "Yes", "Ratio Diff": "-", "Freeleech": "-", "Points": "Yes", "Hit & Run": "-", "Birthdate": "-", "Join": "Application, Invite", "Join Diff": "-", "Updated": "12-29-2019"},
    {"Name": "BakaBT", "Abbreviation": "BBT", "Type": "Anime", "Codebase": "-", "Users": "55,383", "Torrents": "20,611", "Peers": "270,251", "Ratio": "Yes", "Ratio Diff": "Easy", "Freeleech": "-", "Points": "Yes", "Hit & Run": "-", "Birthdate": "2003", "Join": "Application", "Join Diff": "Easy", "Updated": "12-31-2019"},
    {"Name": "Bemaniso", "Abbreviation": "-", "Type": "Games, Music", "Codebase": "Gazelle", "Users": "8,169", "Torrents": "16,539", "Peers": "110,300", "Ratio": "Yes", "Ratio Diff": "-", "Freeleech": "-", "Points": "Yes", "Hit & Run": "-", "Birthdate": "-", "Join": "Invite", "Join Diff": "-", "Updated": "12-30-2019"},
    {"Name": "Beyond-HD", "Abbreviation": "BHD", "Type": "Movie, TV", "Codebase": "UNIT3D", "Users": "15,086", "Torrents": "41,495", "Peers": "170,019", "Ratio": "Yes", "Ratio Diff": "Easy", "Freeleech": "Yes", "Points": "Yes", "Hit & Run": "Yes", "Birthdate": "2012", "Join": "Application, Invite, Recruitment", "Join Diff": "Medium", "Updated": "12-31-2019"},
    {"Name": "Bibliotik", "Abbreviation": "BIB", "Type": "eBooks, Audiobooks", "Codebase": "Custom", "Users": "6,234", "Torrents": "406,797", "Peers": "1,528,856", "Ratio": "Yes", "Ratio Diff": "Hard", "Freeleech": "-", "Points": "No", "Hit & Run": "-", "Birthdate": "2009", "Join": "Invite, Recruitment", "Join Diff": "Hard", "Updated": "12-29-2019"},
    {"Name": "BitSpyder", "Abbreviation": "-", "Type": "E-Learning", "Codebase": "-", "Users": "54,567", "Torrents": "17,234", "Peers": "55,495", "Ratio": "Yes", "Ratio Diff": "Hard", "Freeleech": "-", "Points": "No", "Hit & Run": "-", "Birthdate": "-", "Join": "Invites", "Join Diff": "Medium", "Updated": "01-01-2020"},
    {"Name": "Blutopia", "Abbreviation": "BLU", "Type": "Movie, TV, FANRES", "Codebase": "UNIT3D", "Users": "15,583", "Torrents": "35,817", "Peers": "130,552", "Ratio": "Yes", "Ratio Diff": "Easy", "Freeleech": "Yes", "Points": "Yes", "Hit & Run": "Yes", "Birthdate": "2017", "Join": "Application, Invite, Recruitment", "Join Diff": "Medium", "Updated": "12-31-2019"},
    {"Name": "BroadcasTheNet", "Abbreviation": "BTN", "Type": "TV", "Codebase": "Gazelle", "Users": "35,343", "Torrents": "322,389", "Peers": "3,170,076", "Ratio": "No", "Ratio Diff": "N/A", "Freeleech": "-", "Points": "Yes", "Hit & Run": "-", "Birthdate": "-", "Join": "Invite, Recruitment", "Join Diff": "Hard", "Updated": "12-30-2019"},
    {"Name": "BrokenStones", "Abbreviation": "-", "Type": "Mac Software, Games", "Codebase": "Gazelle", "Users": "12,856", "Torrents": "24,994", "Peers": "246,926", "Ratio": "Yes", "Ratio Diff": "Medium", "Freeleech": "-", "Points": "No", "Hit & Run": "-", "Birthdate": "2004", "Join": "Invite, Recruitment", "Join Diff": "Medium", "Updated": "01-01-2020"},
    {"Name": "CartoonChaos", "Abbreviation": "CC", "Type": "Movie, TV", "Codebase": "-", "Users": "-", "Torrents": "8,579", "Peers": "-", "Ratio": "Yes", "Ratio Diff": "-", "Freeleech": "-", "Points": "Yes", "Hit & Run": "-", "Birthdate": "-", "Join": "Invite, Open", "Join Diff": "-", "Updated": "12-30-2019"},
    {"Name": "CGPeers", "Abbreviation": "CGP", "Type": "CG, VFX", "Codebase": "Gazelle", "Users": "334,345", "Torrents": "33,620", "Peers": "132,058", "Ratio": "No", "Ratio Diff": "N/A", "Freeleech": "-", "Points": "No", "Hit & Run": "-", "Birthdate": "-", "Join": "Invite, Open", "Join Diff": "-", "Updated": "12-30-2019"},
    {"Name": "HQMusic", "Abbreviation": "-", "Type": "Music, Asian", "Codebase": "Gazelle", "Users": "3,607", "Torrents": "4,154", "Peers": "198,641", "Ratio": "Yes", "Ratio Diff": "-", "Freeleech": "Yes", "Points": "No", "Hit & Run": "No", "Birthdate": "-", "Join": "Invite", "Join Diff": "-", "Updated": "01-01-2020"},
    {"Name": "Concertos", "Abbreviation": "-", "Type": "Music", "Codebase": "UNIT3D", "Users": "2,294", "Torrents": "2,761", "Peers": "5,681", "Ratio": "Yes", "Ratio Diff": "Medium", "Freeleech": "Yes", "Points": "Yes", "Hit & Run": "Yes", "Birthdate": "-", "Join": "Invite, Recruitment", "Join Diff": "-", "Updated": "12-30-2019"},
    {"Name": "DeepBassNine", "Abbreviation": "DB9", "Type": "Music", "Codebase": "Gazelle", "Users": "-", "Torrents": "107,839", "Peers": "-", "Ratio": "Yes", "Ratio Diff": "Hard", "Freeleech": "Yes", "Points": "No", "Hit & Run": "No", "Birthdate": "2006", "Join": "Invite", "Join Diff": "Hard", "Updated": "01-01-2020"},
    {"Name": "DesiTorrents", "Abbreviation": "-", "Type": "General, Indian", "Codebase": "-", "Users": "-", "Torrents": "21,100", "Peers": "-", "Ratio": "Yes", "Ratio Diff": "Easy", "Freeleech": "-", "Points": "Yes", "Hit & Run": "-", "Birthdate": "2005", "Join": "Invite", "Join Diff": "Easy", "Updated": "01-01-2020"},
    {"Name": "EfectoDoppler", "Abbreviation": "ED", "Type": "Music", "Codebase": "Gazelle", "Users": "395", "Torrents": "14,822", "Peers": "22,215", "Ratio": "Yes", "Ratio Diff": "-", "Freeleech": "Yes", "Points": "No", "Hit & Run": "No", "Birthdate": "-", "Join": "Invite", "Join Diff": "-", "Updated": "01-01-2020"},
    {"Name": "Empornium", "Abbreviation": "EMP", "Type": "Porn", "Codebase": "Luminance", "Users": "81,839", "Torrents": "405,869", "Peers": "4,008,820", "Ratio": "Yes", "Ratio Diff": "-", "Freeleech": "-", "Points": "Yes", "Hit & Run": "-", "Birthdate": "-", "Join": "Invite, Recruitment", "Join Diff": "-", "Updated": "12-30-2019"},
    {"Name": "ExoticaZ", "Abbreviation": "-", "Type": "Porn", "Codebase": "Custom", "Users": "36,975", "Torrents": "12,064", "Peers": "109,987", "Ratio": "Yes", "Ratio Diff": "-", "Freeleech": "-", "Points": "Yes", "Hit & Run": "-", "Birthdate": "-", "Join": "Application, Invite", "Join Diff": "-", "Updated": "12-29-2019"},
    {"Name": "Femdomcult", "Abbreviation": "FDC", "Type": "Porn", "Codebase": "Gazelle", "Users": "16,354", "Torrents": "48,186", "Peers": "212,685", "Ratio": "Yes", "Ratio Diff": "-", "Freeleech": "-", "Points": "Yes", "Hit & Run": "-", "Birthdate": "-", "Join": "Invite", "Join Diff": "-", "Updated": "12-30-2019"},
    {"Name": "GazelleGames", "Abbreviation": "GGn", "Type": "Games", "Codebase": "Gazelle", "Users": "17,743", "Torrents": "165,131", "Peers": "1,858,547", "Ratio": "Yes", "Ratio Diff": "-", "Freeleech": "-", "Points": "Yes", "Hit & Run": "-", "Birthdate": "-", "Join": "Application, Invite", "Join Diff": "-", "Updated": "12-30-2019"},
    {"Name": "HD-Space", "Abbreviation": "-", "Type": "Movie, TV, Porn", "Codebase": "XBTIT", "Users": "11,910", "Torrents": "87,684", "Peers": "88,419", "Ratio": "Yes", "Ratio Diff": "-", "Freeleech": "-", "Points": "Yes", "Hit & Run": "-", "Birthdate": "-", "Join": "Invite, Recruitment", "Join Diff": "-", "Updated": "12-30-2019"},
    {"Name": "HDBits", "Abbreviation": "HDB", "Type": "Movie, TV", "Codebase": "XBTIT", "Users": "17,702", "Torrents": "284,908", "Peers": "", "Ratio": "Yes", "Ratio Diff": "Medium", "Freeleech": "-", "Points": "Yes", "Hit & Run": "-", "Birthdate": "-", "Join": "Invite", "Join Diff": "Hard", "Updated": "12-31-2019"},
    {"Name": "HDChina", "Abbreviation": "HDC", "Type": "General, Chinese", "Codebase": "NexusPHP", "Users": "22,171", "Torrents": "78,239", "Peers": "-", "Ratio": "Yes", "Ratio Diff": "Easy", "Freeleech": "-", "Points": "Yes", "Hit & Run": "-", "Birthdate": "-", "Join": "Invite, Recruitment", "Join Diff": "-", "Updated": "01-09-2020"},
    {"Name": "HDTorrents", "Abbreviation": "HDT", "Type": "Movie, TV, Sports", "Codebase": "XBTIT", "Users": "18,695", "Torrents": "171,565", "Peers": "493,306", "Ratio": "Yes", "Ratio Diff": "-", "Freeleech": "-", "Points": "Yes", "Hit & Run": "-", "Birthdate": "-", "Join": "Application, Donation, Invite", "Join Diff": "-", "Updated": "12-29-2019"},
    {"Name": "IPTorrents", "Abbreviation": "IPT", "Type": "General", "Codebase": "-", "Users": "-", "Torrents": "971,790", "Peers": "-", "Ratio": "Yes", "Ratio Diff": "Easy", "Freeleech": "-", "Points": "Yes", "Hit & Run": "-", "Birthdate": "-", "Join": "Application, Invite", "Join Diff": "-", "Updated": "12-30-2019"},
    {"Name": "IndieTorrents", "Abbreviation": "IP", "Type": "Music", "Codebase": "Gazelle", "Users": "5,625", "Torrents": "11,596", "Peers": "33,401", "Ratio": "Yes", "Ratio Diff": "Hard", "Freeleech": "Yes", "Points": "No", "Hit & Run": "No", "Birthdate": "-", "Join": "Invite", "Join Diff": "-", "Updated": "01-01-2020"},
    {"Name": "JPopSuki", "Abbreviation": "JPS", "Type": "Music, Asian", "Codebase": "Gazelle", "Users": "178,370", "Torrents": "281,182", "Peers": "1,498,882", "Ratio": "Yes", "Ratio Diff": "Easy", "Freeleech": "Yes", "Points": "Yes", "Hit & Run": "No", "Birthdate": "-", "Join": "Invite, Recruitment", "Join Diff": "Easy", "Updated": "12-30-2019"},
    {"Name": "JPTVTs", "Abbreviation": "-", "Type": "TV", "Codebase": "Custom", "Users": "566", "Torrents": "23,743", "Peers": "-", "Ratio": "Yes", "Ratio Diff": "Easy", "Freeleech": "-", "Points": "No", "Hit & Run": "-", "Birthdate": "2017", "Join": "Invite", "Join Diff": "Easy", "Updated": "12-30-2019"},
    {"Name": "KEEP FRIENDS", "Abbreviation": "FRDS", "Type": "General, Chinese", "Codebase": "NexusPHP", "Users": "4,450", "Torrents": "9,541", "Peers": "314,048", "Ratio": "Yes", "Ratio Diff": "Easy", "Freeleech": "-", "Points": "Yes", "Hit & Run": "-", "Birthdate": "-", "Join": "Invite", "Join Diff": "-", "Updated": "01-09-2020"},
    {"Name": "LegacyHD", "Abbreviation": "LHD", "Type": "General", "Codebase": "UNIT3D", "Users": "102", "Torrents": "1,591", "Peers": "3,422", "Ratio": "Yes", "Ratio Diff": "Easy", "Freeleech": "Yes", "Points": "Yes", "Hit & Run": "Yes", "Birthdate": "-", "Join": "Application", "Join Diff": "-", "Updated": "12-29-2019"},
    {"Name": "KrayTracker", "Abbreviation": "KT", "Type": "Music", "Codebase": "Gazelle", "Users": "1,290", "Torrents": "8,375", "Peers": "4,721", "Ratio": "Yes", "Ratio Diff": "-", "Freeleech": "Yes", "Points": "Yes", "Hit & Run": "No", "Birthdate": "-", "Join": "Invite", "Join Diff": "-", "Updated": "01-01-2020"},
    {"Name": "Libble", "Abbreviation": "-", "Type": "Music", "Codebase": "Gazelle", "Users": "2,598", "Torrents": "35,456", "Peers": "44,367", "Ratio": "No", "Ratio Diff": "-", "Freeleech": "Yes", "Points": "No", "Hit & Run": "Yes", "Birthdate": "2004", "Join": "Invite", "Join Diff": "-", "Updated": "01-01-2020"},
    {"Name": "LostFilmTV", "Abbreviation": "-", "Type": "Movie, TV, Russian", "Codebase": "-", "Users": "-", "Torrents": "-", "Peers": "-", "Ratio": "No", "Ratio Diff": "-", "Freeleech": "-", "Points": "No", "Hit & Run": "-", "Birthdate": "-", "Join": "Open", "Join Diff": "-", "Updated": "01-09-2020"},
    {"Name": "LzTr", "Abbreviation": "N/A", "Type": "Music", "Codebase": "Gazelle", "Users": "1,099", "Torrents": "19,942", "Peers": "28,024", "Ratio": "Yes", "Ratio Diff": "Medium", "Freeleech": "Yes", "Points": "Yes", "Hit & Run": "Yes", "Birthdate": "-", "Join": "Application, Invite", "Join Diff": "-", "Updated": "12-30-2019"},
    {"Name": "Morethantv", "Abbreviation": "MTV", "Type": "TV, Movie", "Codebase": "Gazelle", "Users": "9,718", "Torrents": "115,825", "Peers": "253,234", "Ratio": "No", "Ratio Diff": "N/A", "Freeleech": "-", "Points": "Yes", "Hit & Run": "-", "Birthdate": "2015", "Join": "Application, Invite, Recruitment", "Join Diff": "Easy", "Updated": "12-30-2019"},
    {"Name": "MyAnonaMouse", "Abbreviation": "MAM", "Type": "eBooks, Audiobooks", "Codebase": "TBDev", "Users": "56,355", "Torrents": "514,371", "Peers": "4,673,528", "Ratio": "Yes", "Ratio Diff": "Easy", "Freeleech": "-", "Points": "Yes", "Hit & Run": "-", "Birthdate": "2008", "Join": "Interview, Invite, Recruitment", "Join Diff": "Easy", "Updated": "01-01-2020"},
    {"Name": "MySpleen", "Abbreviation": "MS", "Type": "TV, Movie, Vintage", "Codebase": "-", "Users": "32,404", "Torrents": "27,712", "Peers": "54,332", "Ratio": "Yes", "Ratio Diff": "-", "Freeleech": "-", "Points": "No", "Hit & Run": "-", "Birthdate": "2004", "Join": "Closed", "Join Diff": "Impossible", "Updated": "12-31-2019"},
    {"Name": "M-Team", "Abbreviation": "MTTP", "Type": "General, Chinese", "Codebase": "NexusPHP", "Users": "40,803", "Torrents": "305,064", "Peers": "1,885,841", "Ratio": "Yes", "Ratio Diff": "Easy", "Freeleech": "-", "Points": "Yes", "Hit & Run": "-", "Birthdate": "-", "Join": "Invite, Recruitment", "Join Diff": "-", "Updated": "12-31-2019"},
    {"Name": "Nebulance", "Abbreviation": "NBL", "Type": "TV", "Codebase": "Gazelle", "Users": "5,746", "Torrents": "16,745", "Peers": "57,873", "Ratio": "No", "Ratio Diff": "N/A", "Freeleech": "-", "Points": "Yes", "Hit & Run": "-", "Birthdate": "2014", "Join": "Application, Invite, Recruitment", "Join Diff": "Easy", "Updated": "12-30-2019"},
    {"Name": "NotWhatCD", "Abbreviation": "NWCD", "Type": "Music", "Codebase": "Gazelle", "Users": "2,846", "Torrents": "55,978", "Peers": "168,960", "Ratio": "Yes", "Ratio Diff": "-", "Freeleech": "-", "Points": "Yes", "Hit & Run": "-", "Birthdate": "2016", "Join": "Invite, Recruitment", "Join Diff": "-", "Updated": "12-30-2019"},
    {"Name": "Oppaitime", "Abbreviation": "OT", "Type": "Porn", "Codebase": "Gazelle", "Users": "2,419", "Torrents": "38,435", "Peers": "-", "Ratio": "Yes", "Ratio Diff": "Easy", "Freeleech": "-", "Points": "Yes", "Hit & Run": "-", "Birthdate": "-", "Join": "Application, Invite", "Join Diff": "Easy", "Updated": "12-30-2019"},
    {"Name": "Orpheus", "Abbreviation": "OPS", "Type": "Music", "Codebase": "Gazelle", "Users": "13,911", "Torrents": "643,096", "Peers": "1,729,046", "Ratio": "Yes", "Ratio Diff": "-", "Freeleech": "Yes", "Points": "Yes", "Hit & Run": "No", "Birthdate": "2018", "Join": "Application, Invite", "Join Diff": "-", "Updated": "12-30-2019"},
    {"Name": "OurBits", "Abbreviation": "OB", "Type": "Movie, TV", "Codebase": "NexusPHP", "Users": "-", "Torrents": "-", "Peers": "-", "Ratio": "-", "Ratio Diff": "-", "Freeleech": "-", "Points": "-", "Hit & Run": "-", "Birthdate": "-", "Join": "-", "Join Diff": "-", "Updated": "12-29-2019"},
    {"Name": "PassThePopcorn", "Abbreviation": "PTP", "Type": "Movie", "Codebase": "Gazelle", "Users": "38,996", "Torrents": "544,485", "Peers": "3,334,582", "Ratio": "Yes", "Ratio Diff": "-", "Freeleech": "Yes", "Points": "Yes", "Hit & Run": "Yes", "Birthdate": "2008", "Join": "Recruitment", "Join Diff": "-", "Updated": "12-29-2019"},
    {"Name": "PirateTheNet", "Abbreviation": "PTN", "Type": "Movie, TV", "Codebase": "-", "Users": "2,891", "Torrents": "16,819", "Peers": "19,365", "Ratio": "Yes", "Ratio Diff": "-", "Freeleech": "-", "Points": "Yes", "Hit & Run": "Yes", "Birthdate": "-", "Join": "Invite, Open", "Join Diff": "-", "Updated": "01-13-2020"},
    {"Name": "PixelCove", "Abbreviation": "PxC", "Type": "Games", "Codebase": "Gazelle", "Users": "1,124", "Torrents": "1,851", "Peers": "10,068", "Ratio": "Yes", "Ratio Diff": "-", "Freeleech": "-", "Points": "Yes", "Hit & Run": "-", "Birthdate": "-", "Join": "Invite, Recruitment", "Join Diff": "-", "Updated": "12-30-2019"},
    {"Name": "PolishSource", "Abbreviation": "PS", "Type": "General, Polish", "Codebase": "-", "Users": "29,127", "Torrents": "137,485", "Peers": "132,756", "Ratio": "No", "Ratio Diff": "N/A", "Freeleech": "-", "Points": "Yes", "Hit & Run": "-", "Birthdate": "2008", "Join": "Invite, Open", "Join Diff": "Easy", "Updated": "01-01-2020"},
    {"Name": "PolishTracker", "Abbreviation": "-", "Type": "General, Polish", "Codebase": "-", "Users": "-", "Torrents": "2993", "Peers": "-", "Ratio": "Yes", "Ratio Diff": "-", "Freeleech": "No", "Points": "Yes", "Hit & Run": "No", "Birthdate": "2004", "Join": "Invite", "Join Diff": "Easy", "Updated": "01-09-2020"},
    {"Name": "Pornbay", "Abbreviation": "PB", "Type": "Porn", "Codebase": "Gazelle", "Users": "66,950", "Torrents": "142,605", "Peers": "825,564", "Ratio": "Yes", "Ratio Diff": "Easy", "Freeleech": "-", "Points": "Yes", "Hit & Run": "-", "Birthdate": "-", "Join": "Invite, Open", "Join Diff": "-", "Updated": "12-30-2019"},
    {"Name": "PornoLab", "Abbreviation": "PL", "Type": "Porn, Russian", "Codebase": "-", "Users": "3,281,320", "Torrents": "613,449", "Peers": "-", "Ratio": "Yes", "Ratio Diff": "Easy", "Freeleech": "-", "Points": "Yes", "Hit & Run": "-", "Birthdate": "2008", "Join": "Open", "Join Diff": "Easy", "Updated": "01-01-2020"},
    {"Name": "PrivateHD", "Abbreviation": "PHD", "Type": "Movie, TV, OSTs", "Codebase": "Custom", "Users": "42,493", "Torrents": "41,263", "Peers": "293,941", "Ratio": "Yes", "Ratio Diff": "-", "Freeleech": "-", "Points": "Yes", "Hit & Run": "-", "Birthdate": "-", "Join": "Application, Invite", "Join Diff": "-", "Updated": "12-29-2019"},
    {"Name": "PsyTorrents", "Abbreviation": "PsyT", "Type": "Music", "Codebase": "Gazelle", "Users": "1,757", "Torrents": "13,122", "Peers": "49,316", "Ratio": "Yes", "Ratio Diff": "-", "Freeleech": "Yes", "Points": "No", "Hit & Run": "No", "Birthdate": "-", "Join": "Invite", "Join Diff": "-", "Updated": "01-01-2020"},
    {"Name": "PTFiles", "Abbreviation": "PTF", "Type": "Movie, TV, Music, Porn", "Codebase": "Custom", "Users": "4,457", "Torrents": "12,519", "Peers": "16,835", "Ratio": "Yes", "Ratio Diff": "-", "Freeleech": "Yes", "Points": "Yes", "Hit & Run": "Yes", "Birthdate": "-", "Join":"Application, Invite", "Join Diff": "Easy", "Updated": "01-13-2020"},
    {"Name": "PuroVicio", "Abbreviation": "PRV", "Type": "Movie, TV", "Codebase": "UNIT3D", "Users": "2,720", "Torrents": "3,073", "Peers": "3,598", "Ratio": "Yes", "Ratio Diff": "-", "Freeleech": "-", "Points": "Yes", "Hit & Run": "-", "Birthdate": "2018", "Join": "Invite, Open", "Join Diff": "Easy", "Updated": "12-29-2019"},
    {"Name": "Racing4Everyone", "Abbreviation": "R4E", "Type": "Sports", "Codebase": "UNIT3D", "Users": "3,402", "Torrents": "4,423", "Peers": "9,690", "Ratio": "Yes", "Ratio Diff": "Easy", "Freeleech": "-", "Points": "Yes", "Hit & Run": "-", "Birthdate": "2018", "Join": "Application, Invite, Recruitment", "Join Diff": "-", "Updated": "12-29-2019"},
    {"Name": "RacingForMe", "Abbreviation": "RFM", "Type": "Sports", "Codebase": "Custom", "Users": "-", "Torrents": "-", "Peers": "-", "Ratio": "Yes", "Ratio Diff": "Medium", "Freeleech": "-", "Points": "No", "Hit & Run": "-", "Birthdate": "2006", "Join": "Invite", "Join Diff": "-", "Updated": "01-01-2020"},
    {"Name": "Redacted", "Abbreviation": "RED", "Type": "Music", "Codebase": "Gazelle", "Users": "34,813", "Torrents": "1,778,901", "Peers": "5,042,899", "Ratio": "Yes", "Ratio Diff": "-", "Freeleech": "No", "Points": "No", "Hit & Run": "No", "Birthdate": "2016", "Join": "Application, Invite", "Join Diff": "-", "Updated": "12-29-2019"},
    {"Name": "RuTracker", "Abbreviation": "-", "Type": "General, Russian", "Codebase": "-", "Users": "15,800,000", "Torrents": "1,950,000", "Peers": "-", "Ratio": "No", "Ratio Diff": "N/A", "Freeleech": "-", "Points": "Yes", "Hit & Run": "-", "Birthdate": "2004", "Join": "Open", "Join Diff": "Easy", "Updated": "01-01-2020"},
    {"Name": "Secret Cinema", "Abbreviation": "SC", "Type": "Movie", "Codebase": "Gazelle", "Users": "2,499", "Torrents": "21,997", "Peers": "34,637", "Ratio": "No", "Ratio Diff": "N/A", "Freeleech": "-", "Points": "Yes", "Hit & Run": "-", "Birthdate": "-", "Join": "-", "Join Diff": "-", "Updated": "12-30-2019"},
    {"Name": "ShareUniversity", "Abbreviation": "-", "Type": "General", "Codebase": "UNIT3D", "Users": "-", "Torrents": "-", "Peers": "-", "Ratio": "Yes", "Ratio Diff": "-", "Freeleech": "-", "Points": "Yes", "Hit & Run": "-", "Birthdate": "-", "Join": "-", "Join Diff": "-", "Updated": "12-29-2019"},
    {"Name": "ShareWood", "Abbreviation": "SHW", "Type": "General", "Codebase": "UNIT3D", "Users": "-", "Torrents": "-", "Peers": "-", "Ratio": "Yes", "Ratio Diff": "-", "Freeleech": "-", "Points": "Yes", "Hit & Run": "-", "Birthdate": "-", "Join": "-", "Join Diff": "-", "Updated": "12-29-2019"},
    {"Name": "SocietyGlitch", "Abbreviation": "SG", "Type": "Miscellaneous", "Codebase": "-", "Users": "920", "Torrents": "560", "Peers": "1,268", "Ratio": "No", "Ratio Diff": "N/A", "Freeleech": "-", "Points": "No", "Hit & Run": "-", "Birthdate": "-", "Join": "Application, Invite", "Join Diff": "-", "Updated": "12-30-2019"},
    {"Name": "SportsCult", "Abbreviation": "SC", "Type": "Sports", "Codebase": "-", "Users": "29,632", "Torrents": "76,367", "Peers": "105,057", "Ratio": "Yes", "Ratio Diff": "Medium", "Freeleech": "-", "Points": "Yes", "Hit & Run": "Yes", "Birthdate": "-", "Join": "Invite", "Join Diff": "-", "Updated": "01-16-2020"},
    {"Name": "SpringSunday", "Abbreviation": "SSD", "Type": "General, Chinese", "Codebase": "NexusPHP", "Users": "18,849", "Torrents": "56,527", "Peers": "433,645", "Ratio": "Yes", "Ratio Diff": "Easy", "Freeleech": "-", "Points": "Yes", "Hit & Run": "-", "Birthdate": "-", "Join": "Invite, Recruitment", "Join Diff": "-", "Updated": "01-09-2020"},
    {"Name": "SugoiMusic", "Abbreviation": "-", "Type": "Music, Asian", "Codebase": "Gazelle", "Users": "62", "Torrents": "12,003", "Peers": "20,814", "Ratio": "Yes", "Ratio Diff": "-", "Freeleech": "Yes", "Points": "-", "Hit & Run": "-", "Birthdate": "2019", "Join": "Invite", "Join Diff": "-", "Updated": "01-09-2020"},
    {"Name": "TheGeeks", "Abbreviation": "TG", "Type": "E-learning", "Codebase": "TCG", "Users": "-", "Torrents": "72,478", "Peers": "-", "Ratio": "Yes", "Ratio Diff": "Hard", "Freeleech": "-", "Points": "No", "Hit & Run": "-", "Birthdate": "-", "Join": "Application, Invite", "Join Diff": "-", "Updated": "12-30-2019"},
    {"Name": "The Horror Charnel", "Abbreviation": "THC", "Type": "Movie, TV", "Codebase": "-", "Users": "-", "Torrents": "-", "Peers": "-", "Ratio": "Yes", "Ratio Diff": "-", "Freeleech": "-", "Points": "Yes", "Hit & Run": "-", "Birthdate": "-", "Join": "-", "Join Diff": "-", "Updated": "12-29-2019"},
    {"Name": "ThePlace", "Abbreviation": "TP", "Type": "Self-help, PUA", "Codebase": "TCG", "Users": "-", "Torrents": "64,567", "Peers": "-", "Ratio": "Yes", "Ratio Diff": "Hard", "Freeleech": "-", "Points": "No", "Hit & Run": "-", "Birthdate": "-", "Join": "Application, Invite", "Join Diff": "-", "Updated": "12-30-2019"},
    {"Name": "TorrentBD", "Abbreviation": "TBD", "Type": "General", "Codebase": "-", "Users": "123,467", "Torrents": "243,742", "Peers": "-", "Ratio": "Yes", "Ratio Diff": "Easy", "Freeleech": "-", "Points": "Yes", "Hit & Run": "-", "Birthdate": "2010", "Join": "Invite, Recruitment", "Join Diff": "Easy", "Updated": "12-31-2019"},
    {"Name": "TorrentLeech", "Abbreviation": "TL", "Type": "General", "Codebase": "-", "Users": "-", "Torrents": "1,061,375", "Peers": "-", "Ratio": "Yes", "Ratio Diff": "Medium", "Freeleech": "-", "Points": "Yes", "Hit & Run": "-", "Birthdate": "2005", "Join": "Invite, Open", "Join Diff": "Easy", "Updated": "01-06-2020"},
    {"Name": "ToTheGlory", "Abbreviation": "TTG", "Type": "General, Chinese", "Codebase": "NexusPHP", "Users": "-", "Torrents": "243,749", "Peers": "667,113", "Ratio": "Yes", "Ratio Diff": "Easy", "Freeleech": "-", "Points": "Yes", "Hit & Run": "-", "Birthdate": "2009", "Join": "Invite, Recruitment", "Join Diff": "-", "Updated": "12-31-2019"},
    {"Name": "TV-Vault", "Abbreviation": "TVV", "Type": "Movie, TV", "Codebase": "Gazelle", "Users": "10,497", "Torrents": "47,253", "Peers": "159,848", "Ratio": "Yes", "Ratio Diff": "-", "Freeleech": "-", "Points": "No", "Hit & Run": "-", "Birthdate": "-", "Join": "Invite", "Join Diff": "-", "Updated": "01-01-2020"},
    {"Name": "U2", "Abbreviation": "U2", "Type": "Anime", "Codebase": "NexusPHP", "Users": "8,160", "Torrents": "34,554", "Peers": "413,333", "Ratio": "Yes", "Ratio Diff": "Easy", "Freeleech": "-", "Points": "Yes", "Hit & Run": "-", "Birthdate": "-", "Join": "Invite", "Join Diff": "-", "Updated": "12-30-2019"},
    {"Name": "UHDBits", "Abbreviation": "UHD", "Type": "Movie, TV", "Codebase": "Gazelle", "Users": "6,559", "Torrents": "29,476", "Peers": "52,150", "Ratio": "Yes", "Ratio Diff": "-", "Freeleech": "-", "Points": "Yes", "Hit & Run": "-", "Birthdate": "2012", "Join": "Application, Invite", "Join Diff": "-", "Updated": "12-29-2019"},
    {"Name": "XtremeWrestlingTorrents", "Abbreviation": "XWT", "Type": "Wrestling/MMA", "Codebase": "-", "Users": "322,104", "Torrents": "18,946", "Peers": "80,218", "Ratio": "Yes", "Ratio Diff": "-", "Freeleech": "-", "Points": "No", "Hit & Run": "-", "Birthdate": "-", "Join": "Invite, Open", "Join Diff": "Easy", "Updated": "01-13-2020"}
  ]
}
